slim_compose-2.0.8.dist-info/METADATA
slim_compose-2.0.8.dist-info/WHEEL
slim_compose-2.0.8.dist-info/entry_points.txt
slim_compose-2.0.8.dist-info/licenses/LICENSE
slim_compose/__init__.py
slim_compose/args.py
slim_compose/main.py
slim_compose/utils.py
slim_compose-2.0.8.dist-info/RECORD
