Metadata-Version: 2.1
Name: slim-compose
Version: 2.0.8
Summary: Simple management tool for podman pods, pure Python, no third-party dependencies.
Author: xfoobar
License: MIT
Classifier: Programming Language :: Python
Classifier: Operating System :: OS Independent
Classifier: Programming Language :: Python :: Implementation
Classifier: License :: OSI Approved :: MIT License
Requires-Python: >=3.10
